matrices/__init__.py
matrices/matrices.py
matrices/matrices.pyi
matrices/protocols.py
matrices/protocols.pyi
matrices/py.typed
matrices/rule.py
matrices/rule.pyi
matrices/shape.py
matrices/shape.pyi
matrices/utilities.py
matrices/utilities.pyi
matrices/tests/__init__.py
matrices/tests/test_matrices.py
matrices/tests/test_protocols.py
matrices_py-0.2.3.dist-info/LICENSE
matrices_py-0.2.3.dist-info/METADATA
matrices_py-0.2.3.dist-info/WHEEL
matrices_py-0.2.3.dist-info/top_level.txt
matrices_py-0.2.3.dist-info/RECORD
