Metadata-Version: 2.1
Name: matrices-py
Version: 0.2.3
Summary: Dynamic, vectorized sequence types in ≤ 2 dimensions.
Author: Braedyn L
License: MIT License
Project-URL: Homepage, https://github.com/braedynl/matrices-py
Project-URL: Source, https://github.com/braedynl/matrices-py
Project-URL: Documentation, https://github.com/braedynl/matrices-py/wiki
Project-URL: Bug Tracker, https://github.com/braedynl/matrices-py/issues
Keywords: matrices,matrix,vectors,vector,vectorization
Classifier: Programming Language :: Python :: 3
Classifier: Programming Language :: Python :: 3.10
Classifier: Programming Language :: Python :: 3.11
Classifier: License :: OSI Approved :: MIT License
Classifier: Operating System :: OS Independent
Classifier: Topic :: Software Development :: Libraries :: Python Modules
Requires-Python: >=3.10
License-File: LICENSE
